investment_calculator/Lumpsum.py
investment_calculator/NumeralSystem.py
investment_calculator/SIP.py
investment_calculator/SWP.py
investment_calculator/__init__.py
investment_calculator-1.1.0.dist-info/METADATA
investment_calculator-1.1.0.dist-info/WHEEL
investment_calculator-1.1.0.dist-info/top_level.txt
investment_calculator-1.1.0.dist-info/RECORD
